passerts/__init__.py
passerts/asserts.py
passerts-0.0.2.dist-info/LICENSE
passerts-0.0.2.dist-info/METADATA
passerts-0.0.2.dist-info/WHEEL
passerts-0.0.2.dist-info/top_level.txt
passerts-0.0.2.dist-info/RECORD
